iapp_ai/__init__.py
iapp_ai/module_api.py
iapp_ai-1.4.0.dist-info/AUTHORS.rst
iapp_ai-1.4.0.dist-info/LICENSE
iapp_ai-1.4.0.dist-info/METADATA
iapp_ai-1.4.0.dist-info/WHEEL
iapp_ai-1.4.0.dist-info/top_level.txt
iapp_ai-1.4.0.dist-info/RECORD
