Metadata-Version: 2.1
Name: iapp_ai
Version: 1.4.0
Summary: iApp AI API pip package
Home-page: https://github.com/iapp-technology/iapp_ai
Author: Kobkrit Viriyayudhakorn
Author-email: kobkrit@iapp.co.th
License: MIT license
Keywords: iapp_ai
Classifier: Development Status :: 2 - Pre-Alpha
Classifier: Intended Audience :: Developers
Classifier: License :: OSI Approved :: MIT License
Classifier: Natural Language :: English
Classifier: Programming Language :: Python :: 3
Classifier: Programming Language :: Python :: 3.6
Classifier: Programming Language :: Python :: 3.7
Classifier: Programming Language :: Python :: 3.8
Requires-Python: >=3.6
License-File: LICENSE
License-File: AUTHORS.rst
